{
  "heroes": [
    {
      "id": 1,
      "name": "Первый герой",
      "description": "Первый герой в рейтинге!",
      "element": "fire"
    },
    {
      "id": "b288890d-805d-4017-9baf-13dac0ba9ece",
      "name": "Viktor",
      "description": "fbdryjtjdtj",
      "element": "wind"
    },
    {
      "id": "24aae38d-7d6c-4145-ac74-0863f5fd1e39",
      "name": "xdtdrtb",
      "description": "fyikryumdtn",
      "element": "wind"
    }
  ],
  "filters": [
    {
      "name": "all",
      "label": "Все",
      "className": "btn-outline-dark"
    },
    {
      "name": "fire",
      "label": "Огонь",
      "className": "btn-danger"
    },
    {
      "name": "water",
      "label": "Вода",
      "className": "btn-primary"
    },
    {
      "name": "wind",
      "label": "Ветер",
      "className": "btn-success"
    },
    {
      "name": "earth",
      "label": "Земля",
      "className": "btn-secondary"
    }
  ]
}